doFolder/__init__.py
doFolder/__pkginfo__.py
doFolder/compare.py
doFolder/enums.py
doFolder/exception.py
doFolder/fileSystem.py
doFolder/globalType.py
doFolder/hashing.py
doFolder/path.py
dofolder-2.2.5.dist-info/licenses/LICENSE
dofolder-2.2.5.dist-info/METADATA
dofolder-2.2.5.dist-info/WHEEL
dofolder-2.2.5.dist-info/top_level.txt
dofolder-2.2.5.dist-info/RECORD
