Metadata-Version: 2.4
Name: doFolder
Version: 2.2.5
Summary: Manage files more easily
Author-email: kuankuan <2163826131@qq.com>
License-Expression: MulanPSL-2.0
Project-URL: Repository, https://github.com/kuankuan2007/do-folder
Project-URL: Issues, https://github.com/kuankuan2007/do-folder/issues
Project-URL: Documentation, https://do-folder.doc.kuankuan.site
Keywords: folder,file,manage,filesystem,directory
Classifier: Natural Language :: English
Classifier: Development Status :: 5 - Production/Stable
Classifier: Intended Audience :: Developers
Classifier: Programming Language :: Python :: 3
Classifier: Operating System :: MacOS
Classifier: Operating System :: POSIX :: Linux
Classifier: Operating System :: Microsoft :: Windows
Requires-Python: >=3.8
License-File: LICENSE
Requires-Dist: exceptiongroup
Requires-Dist: typing_extensions>=4.10.0
Requires-Dist: deprecated
Dynamic: license-file
